src/__init__.py
src/_version.py
src/tamppa.py
tamppa/__init__.py
tamppa/_version.py
tamppa/tamppa_code.py
tamppa/tamppa_code_mem.py
tamppa/tamppa_code_tim.py
TAMPPA-0.0.1.dist-info/LICENSE
TAMPPA-0.0.1.dist-info/METADATA
TAMPPA-0.0.1.dist-info/WHEEL
TAMPPA-0.0.1.dist-info/top_level.txt
TAMPPA-0.0.1.dist-info/RECORD
