Metadata-Version: 2.1
Name: TAMPPA
Version: 0.0.1
Summary: Time And Memory Profile Parser
Home-page: https://github.com/pra-dan/TAMPPA
Author: Prashant Dandriyal
Author-email: prashantdandriyal7@gmail.com
License: MPL
Keywords: memory,parsing,parser,timing,timer,profiling,profiler,line_profiler
Platform: UNKNOWN
Classifier: Programming Language :: Python :: 3
Classifier: License :: OSI Approved :: Mozilla Public License 2.0 (MPL 2.0)
Classifier: Operating System :: OS Independent
Requires-Python: >=3.6
Requires-Dist: matplotlib
Requires-Dist: pandas
